{
    "steps": [
        {
            "name": "Step1",
            "limb_motions": {
                "RIGHTARM_FULL": {
                    "part": {
                        "name": "RIGHTARM_FULL",
                        "robot_part": "right_arm",
                        "joints_nr": 16,
                        "joints_list": [
                            0,
                            1,
                            2,
                            3,
                            4,
                            5,
                            6,
                            7,
                            8,
                            9,
                            10,
                            11,
                            12,
                            13,
                            14,
                            15
                        ],
                        "joints_speed": [
                            10,
                            10,
                            10,
                            10,
                            30,
                            30,
                            30,
                            100,
                            100,
                            100,
                            100,
                            100,
                            100,
                            100,
                            100,
                            100
                        ]
                    },
                    "checkpoints": [
                        {
                            "pose": {
                                "target_joints": [
                                    -90.0,
                                    20.0,
                                    10.0,
                                    90.0,
                                    0.0,
                                    0.0,
                                    0.0,
                                    60.0,
                                    20.0,
                                    20.0,
                                    20.0,
                                    10.0,
                                    10.0,
                                    10.0,
                                    10.0,
                                    10.0
                                ],
                                "joints_list": [
                                    0,
                                    1,
                                    2,
                                    3,
                                    4,
                                    5,
                                    6,
                                    7,
                                    8,
                                    9,
                                    10,
                                    11,
                                    12,
                                    13,
                                    14,
                                    15
                                ]
                            },
                            "duration": 1.0,
                            "timeout": 30.0,
                            "joints_speed": [
                                10,
                                10,
                                10,
                                10,
                                30,
                                30,
                                30,
                                100,
                                100,
                                100,
                                100,
                                100,
                                100,
                                100,
                                100,
                                100
                            ]
                        },
                        {
                            "pose": {
                                "target_joints": [
                                    0.0,
                                    15.0,
                                    0.0,
                                    25.0,
                                    0.0,
                                    0.0,
                                    0.0,
                                    60.0,
                                    20.0,
                                    0.0,
                                    0.0,
                                    0.0,
                                    0.0,
                                    0.0,
                                    0.0,
                                    0.0
                                ],
                                "joints_list": [
                                    0,
                                    1,
                                    2,
                                    3,
                                    4,
                                    5,
                                    6,
                                    7,
                                    8,
                                    9,
                                    10,
                                    11,
                                    12,
                                    13,
                                    14,
                                    15
                                ]
                            },
                            "duration": 1.0,
                            "timeout": 30.0,
                            "joints_speed": [
                                10,
                                10,
                                10,
                                10,
                                30,
                                30,
                                30,
                                100,
                                100,
                                100,
                                100,
                                100,
                                100,
                                100,
                                100,
                                100
                            ]
                        }
                    ]
                },
                "LEFTARM_FULL": {
                    "part": {
                        "name": "LEFTARM_FULL",
                        "robot_part": "left_arm",
                        "joints_nr": 16,
                        "joints_list": [
                            0,
                            1,
                            2,
                            3,
                            4,
                            5,
                            6,
                            7,
                            8,
                            9,
                            10,
                            11,
                            12,
                            13,
                            14,
                            15
                        ],
                        "joints_speed": [
                            10,
                            10,
                            10,
                            10,
                            30,
                            30,
                            30,
                            100,
                            100,
                            100,
                            100,
                            100,
                            100,
                            100,
                            100,
                            100
                        ]
                    },
                    "checkpoints": [
                        {
                            "pose": {
                                "target_joints": [
                                    -90.0,
                                    20.0,
                                    10.0,
                                    90.0,
                                    0.0,
                                    0.0,
                                    0.0,
                                    60.0,
                                    20.0,
                                    20.0,
                                    20.0,
                                    10.0,
                                    10.0,
                                    10.0,
                                    10.0,
                                    10.0
                                ],
                                "joints_list": [
                                    0,
                                    1,
                                    2,
                                    3,
                                    4,
                                    5,
                                    6,
                                    7,
                                    8,
                                    9,
                                    10,
                                    11,
                                    12,
                                    13,
                                    14,
                                    15
                                ]
                            },
                            "duration": 1.0,
                            "timeout": 30.0,
                            "joints_speed": [
                                10,
                                10,
                                10,
                                10,
                                30,
                                30,
                                30,
                                100,
                                100,
                                100,
                                100,
                                100,
                                100,
                                100,
                                100,
                                100
                            ]
                        },
                        {
                            "pose": {
                                "target_joints": [
                                    0.0,
                                    15.0,
                                    0.0,
                                    25.0,
                                    0.0,
                                    0.0,
                                    0.0,
                                    60.0,
                                    20.0,
                                    0.0,
                                    0.0,
                                    0.0,
                                    0.0,
                                    0.0,
                                    0.0,
                                    0.0
                                ],
                                "joints_list": [
                                    0,
                                    1,
                                    2,
                                    3,
                                    4,
                                    5,
                                    6,
                                    7,
                                    8,
                                    9,
                                    10,
                                    11,
                                    12,
                                    13,
                                    14,
                                    15
                                ]
                            },
                            "duration": 1.0,
                            "timeout": 30.0,
                            "joints_speed": [
                                10,
                                10,
                                10,
                                10,
                                30,
                                30,
                                30,
                                100,
                                100,
                                100,
                                100,
                                100,
                                100,
                                100,
                                100,
                                100
                            ]
                        }
                    ]
                }
            },
            "gaze_motion": null,
            "custom_calls": [
                {
                    "target": "gaze.lookAtAbsAngles",
                    "args": [
                        0.0,
                        15.0,
                        0.0
                    ]
                },
                {
                    "target": "emo.neutral",
                    "args": []
                }
            ],
            "offset_ms": null
        },
        {
            "name": "Step2",
            "limb_motions": {
                "LEFTARM_FULL": {
                    "part": {
                        "name": "LEFTARM_FULL",
                        "robot_part": "left_arm",
                        "joints_nr": 16,
                        "joints_list": [
                            0,
                            1,
                            2,
                            3,
                            4,
                            5,
                            6,
                            7,
                            8,
                            9,
                            10,
                            11,
                            12,
                            13,
                            14,
                            15
                        ],
                        "joints_speed": [
                            10,
                            10,
                            10,
                            10,
                            30,
                            30,
                            30,
                            100,
                            100,
                            100,
                            100,
                            100,
                            100,
                            100,
                            100,
                            100
                        ]
                    },
                    "checkpoints": [
                        {
                            "pose": {
                                "target_joints": [
                                    -90.0,
                                    20.0,
                                    10.0,
                                    90.0,
                                    0.0,
                                    0.0,
                                    0.0,
                                    60.0,
                                    20.0,
                                    20.0,
                                    20.0,
                                    10.0,
                                    10.0,
                                    10.0,
                                    10.0,
                                    10.0
                                ],
                                "joints_list": [
                                    0,
                                    1,
                                    2,
                                    3,
                                    4,
                                    5,
                                    6,
                                    7,
                                    8,
                                    9,
                                    10,
                                    11,
                                    12,
                                    13,
                                    14,
                                    15
                                ]
                            },
                            "duration": 1.0,
                            "timeout": 30.0,
                            "joints_speed": [
                                10,
                                10,
                                10,
                                10,
                                30,
                                30,
                                30,
                                100,
                                100,
                                100,
                                100,
                                100,
                                100,
                                100,
                                100,
                                100
                            ]
                        },
                        {
                            "pose": {
                                "target_joints": [
                                    0.0,
                                    15.0,
                                    0.0,
                                    25.0,
                                    0.0,
                                    0.0,
                                    0.0,
                                    60.0,
                                    20.0,
                                    0.0,
                                    0.0,
                                    0.0,
                                    0.0,
                                    0.0,
                                    0.0,
                                    0.0
                                ],
                                "joints_list": [
                                    0,
                                    1,
                                    2,
                                    3,
                                    4,
                                    5,
                                    6,
                                    7,
                                    8,
                                    9,
                                    10,
                                    11,
                                    12,
                                    13,
                                    14,
                                    15
                                ]
                            },
                            "duration": 1.0,
                            "timeout": 30.0,
                            "joints_speed": [
                                10,
                                10,
                                10,
                                10,
                                30,
                                30,
                                30,
                                100,
                                100,
                                100,
                                100,
                                100,
                                100,
                                100,
                                100,
                                100
                            ]
                        }
                    ]
                }
            },
            "gaze_motion": null,
            "custom_calls": [],
            "offset_ms": null
        },
        {
            "name": "Step3",
            "limb_motions": {
                "RIGHTARM_FULL": {
                    "part": {
                        "name": "RIGHTARM_FULL",
                        "robot_part": "right_arm",
                        "joints_nr": 16,
                        "joints_list": [
                            0,
                            1,
                            2,
                            3,
                            4,
                            5,
                            6,
                            7,
                            8,
                            9,
                            10,
                            11,
                            12,
                            13,
                            14,
                            15
                        ],
                        "joints_speed": [
                            10,
                            10,
                            10,
                            10,
                            30,
                            30,
                            30,
                            100,
                            100,
                            100,
                            100,
                            100,
                            100,
                            100,
                            100,
                            100
                        ]
                    },
                    "checkpoints": [
                        {
                            "pose": {
                                "target_joints": [
                                    -90.0,
                                    20.0,
                                    10.0,
                                    90.0,
                                    0.0,
                                    0.0,
                                    0.0,
                                    60.0,
                                    20.0,
                                    20.0,
                                    20.0,
                                    10.0,
                                    10.0,
                                    10.0,
                                    10.0,
                                    10.0
                                ],
                                "joints_list": [
                                    0,
                                    1,
                                    2,
                                    3,
                                    4,
                                    5,
                                    6,
                                    7,
                                    8,
                                    9,
                                    10,
                                    11,
                                    12,
                                    13,
                                    14,
                                    15
                                ]
                            },
                            "duration": 1.0,
                            "timeout": 30.0,
                            "joints_speed": [
                                10,
                                10,
                                10,
                                10,
                                30,
                                30,
                                30,
                                100,
                                100,
                                100,
                                100,
                                100,
                                100,
                                100,
                                100,
                                100
                            ]
                        },
                        {
                            "pose": {
                                "target_joints": [
                                    0.0,
                                    15.0,
                                    0.0,
                                    25.0,
                                    0.0,
                                    0.0,
                                    0.0,
                                    60.0,
                                    20.0,
                                    0.0,
                                    0.0,
                                    0.0,
                                    0.0,
                                    0.0,
                                    0.0,
                                    0.0
                                ],
                                "joints_list": [
                                    0,
                                    1,
                                    2,
                                    3,
                                    4,
                                    5,
                                    6,
                                    7,
                                    8,
                                    9,
                                    10,
                                    11,
                                    12,
                                    13,
                                    14,
                                    15
                                ]
                            },
                            "duration": 1.0,
                            "timeout": 30.0,
                            "joints_speed": [
                                10,
                                10,
                                10,
                                10,
                                30,
                                30,
                                30,
                                100,
                                100,
                                100,
                                100,
                                100,
                                100,
                                100,
                                100,
                                100
                            ]
                        }
                    ]
                },
                "LEFTARM_FULL": {
                    "part": {
                        "name": "LEFTARM_FULL",
                        "robot_part": "left_arm",
                        "joints_nr": 16,
                        "joints_list": [
                            0,
                            1,
                            2,
                            3,
                            4,
                            5,
                            6,
                            7,
                            8,
                            9,
                            10,
                            11,
                            12,
                            13,
                            14,
                            15
                        ],
                        "joints_speed": [
                            10,
                            10,
                            10,
                            10,
                            30,
                            30,
                            30,
                            100,
                            100,
                            100,
                            100,
                            100,
                            100,
                            100,
                            100,
                            100
                        ]
                    },
                    "checkpoints": [
                        {
                            "pose": {
                                "target_joints": [
                                    -90.0,
                                    20.0,
                                    10.0,
                                    90.0,
                                    0.0,
                                    0.0,
                                    0.0,
                                    60.0,
                                    20.0,
                                    20.0,
                                    20.0,
                                    10.0,
                                    10.0,
                                    10.0,
                                    10.0,
                                    10.0
                                ],
                                "joints_list": [
                                    0,
                                    1,
                                    2,
                                    3,
                                    4,
                                    5,
                                    6,
                                    7,
                                    8,
                                    9,
                                    10,
                                    11,
                                    12,
                                    13,
                                    14,
                                    15
                                ]
                            },
                            "duration": 1.0,
                            "timeout": 30.0,
                            "joints_speed": [
                                10,
                                10,
                                10,
                                10,
                                30,
                                30,
                                30,
                                100,
                                100,
                                100,
                                100,
                                100,
                                100,
                                100,
                                100,
                                100
                            ]
                        },
                        {
                            "pose": {
                                "target_joints": [
                                    0.0,
                                    15.0,
                                    0.0,
                                    25.0,
                                    0.0,
                                    0.0,
                                    0.0,
                                    60.0,
                                    20.0,
                                    0.0,
                                    0.0,
                                    0.0,
                                    0.0,
                                    0.0,
                                    0.0,
                                    0.0
                                ],
                                "joints_list": [
                                    0,
                                    1,
                                    2,
                                    3,
                                    4,
                                    5,
                                    6,
                                    7,
                                    8,
                                    9,
                                    10,
                                    11,
                                    12,
                                    13,
                                    14,
                                    15
                                ]
                            },
                            "duration": 1.0,
                            "timeout": 30.0,
                            "joints_speed": [
                                10,
                                10,
                                10,
                                10,
                                30,
                                30,
                                30,
                                100,
                                100,
                                100,
                                100,
                                100,
                                100,
                                100,
                                100,
                                100
                            ]
                        }
                    ]
                }
            },
            "gaze_motion": {
                "checkpoints": [
                    [
                        20.0,
                        0.0,
                        0.0
                    ],
                    [
                        -20.0,
                        0.0,
                        0.0
                    ],
                    [
                        0.0,
                        0.0,
                        0.0
                    ]
                ],
                "lookat_method": "lookAtAbsAngles"
            },
            "custom_calls": [
                {
                    "target": "emo.smile",
                    "args": []
                }
            ],
            "offset_ms": 500
        }
    ],
    "name": "CompleteAction",
    "description": "empty",
    "offset_ms": null
}